evo_schemas/__init__.py
evo_schemas/components/__init__.py
evo_schemas/components/attribute_description.py
evo_schemas/components/attribute_list_property.py
evo_schemas/components/base_attribute.py
evo_schemas/components/base_category_attribute.py
evo_schemas/components/base_continuous_attribute.py
evo_schemas/components/base_object_properties.py
evo_schemas/components/base_spatial_data_properties.py
evo_schemas/components/block_model_attribute.py
evo_schemas/components/block_model_category_attribute.py
evo_schemas/components/block_model_flexible_structure.py
evo_schemas/components/block_model_fully_subblocked_structure.py
evo_schemas/components/block_model_regular_structure.py
evo_schemas/components/block_model_variable_octree_structure.py
evo_schemas/components/bool_attribute.py
evo_schemas/components/bool_time_series.py
evo_schemas/components/bounding_box.py
evo_schemas/components/brep_container.py
evo_schemas/components/category_attribute.py
evo_schemas/components/category_attribute_description.py
evo_schemas/components/category_data.py
evo_schemas/components/category_ensemble.py
evo_schemas/components/category_time_series.py
evo_schemas/components/channel_attribute.py
evo_schemas/components/color_attribute.py
evo_schemas/components/continuous_attribute.py
evo_schemas/components/continuous_ensemble.py
evo_schemas/components/continuous_time_series.py
evo_schemas/components/crs.py
evo_schemas/components/cumulative_distribution_function.py
evo_schemas/components/data_table.py
evo_schemas/components/date_time_attribute.py
evo_schemas/components/desurvey_method.py
evo_schemas/components/distance_table.py
evo_schemas/components/downhole_attributes.py
evo_schemas/components/downhole_direction_vector.py
evo_schemas/components/ellipsoid.py
evo_schemas/components/ellipsoids.py
evo_schemas/components/embedded_line_geometry.py
evo_schemas/components/embedded_mesh_object.py
evo_schemas/components/embedded_polyline_object.py
evo_schemas-2026.1.8.dist-info/licenses/LICENSE.md
evo_schemas-2026.1.8.dist-info/METADATA
evo_schemas-2026.1.8.dist-info/WHEEL
evo_schemas-2026.1.8.dist-info/top_level.txt
evo_schemas-2026.1.8.dist-info/RECORD
