Metadata-Version: 2.4
Name: evo-schemas
Version: 2026.1.8
Summary: Seequent Geoscience Object Schemas define metadata and data serialisation of various geoscience objects.
Author-email: Seequent <support@seequent.com>
Project-URL: Source, https://github.com/SeequentEvo/evo-schemas
Project-URL: Tracker, https://github.com/SeequentEvo/evo-schemas/issues
Project-URL: Homepage, https://www.seequent.com/
Project-URL: Documentation, https://developer.seequent.com/
Classifier: Programming Language :: Python
Classifier: Operating System :: Microsoft :: Windows
Classifier: Operating System :: POSIX
Classifier: Operating System :: Unix
Classifier: Operating System :: MacOS
Classifier: Natural Language :: English
Requires-Python: >=3.10
License-File: LICENSE.md
Requires-Dist: jsonpointer>=2.4
Requires-Dist: rfc3986-validator>=0.1
Provides-Extra: test
Requires-Dist: black==24.10.0; extra == "test"
Requires-Dist: jsonschema==4.17.3; extra == "test"
Requires-Dist: pre-commit==4.0.1; extra == "test"
Requires-Dist: pytest==8.3.4; extra == "test"
Requires-Dist: pytest-subtests==0.13.1; extra == "test"
Requires-Dist: ruff==0.8.1; extra == "test"
Requires-Dist: semver==3.0.2; extra == "test"
Provides-Extra: tools
Requires-Dist: evo-schemas[test]; extra == "tools"
Requires-Dist: GitPython>=3.1.43; extra == "tools"
Requires-Dist: PyGithub>=2.4.0; extra == "tools"
Provides-Extra: examples
Requires-Dist: evo-schemas[test]; extra == "examples"
Requires-Dist: azure-storage-blob; extra == "examples"
Requires-Dist: jupyter; extra == "examples"
Requires-Dist: pandas; extra == "examples"
Requires-Dist: pyarrow; extra == "examples"
Requires-Dist: python-dotenv; extra == "examples"
Provides-Extra: release
Requires-Dist: twine; extra == "release"
Dynamic: license-file
